{
  "Performance Designed Products Faceoff Deluxe+ Audio Wired Controller for Nintendo Switch": {
    "A": "y-mode",
    "B": "b-mode",
    "C": "a-mode",
    "Mode": "start",
    "rz": "r-joy-up-down",
    "Right Thumb": "analog-trig",
    "x": "l-joy-left-right",
    "X": "x-mode",
    "y": "l-joy-up-down",
    "Y": "l-trig-button",
    "Left Thumb 3": "select",
    "z": "r-joy-left-right",
    "Z": "r-trig-button"
  },
  "Gamesir-T4pro_21FD": {
    "A": "a-mode",
    "slider": "analog-trig",
    "B": "b-mode",
    "Start": "start",
    "rz": "r-joy-up-down",
    "Right Thumb": "r-trig-button",
    "x": "l-joy-left-right",
    "X": "x-mode",
    "Select": "select",
    "y": "l-joy-up-down",
    "Y": "y-mode",
    "z": "r-joy-left-right",
    "Left Thumb": "l-trig-button"
  },
  "workspace": {
    "https://gist.github.com/9b7b38fb2e2d3c3a2d3ee734c83b7e9d.git": [
      "GIST: parts that have chamfered",
      "1685815976840"
    ],
    "https://gist.github.com/4814b39ee72e9f590757.git": [
      "GIST: JavaCadExample",
      "1683220578939"
    ],
    "https://github.com/madhephaestus/JavaCVBowler.git": [
      "https://github.com/madhephaestus/JavaCVBowler.git",
      "1684332974335"
    ],
    "https://gist.github.com/c3944b2a203585d969bf.git": [
      "GIST: Lets bring together some of the parts.",
      "1683220514866"
    ],
    "https://github.com/OperationSmallKat/Isis.git": [
      "OperationSmallKat/Isis",
      "1686573044523"
    ],
    "https://github.com/madhephaestus/VoskGroovy.git": [
      "https://github.com/madhephaestus/VoskGroovy.git",
      "1684277563090"
    ],
    "https://github.com/EmmanuelAsumadu/firefightingrobot.git": [
      "EmmanuelAsumadu/firefightingrobot",
      "1685926243297"
    ],
    "https://gist.github.com/f68a68d539234035e328a94a54faff63.git": [
      "GIST: Robot smashes through pile of bricks",
      "1682444850274"
    ],
    "https://github.com/madhephaestus/ESPnetTTS.git": [
      "https://github.com/madhephaestus/ESPnetTTS.git",
      "1684694910930"
    ],
    "https://github.com/Halloween2020TheChild/CoquiDocker.git": [
      "Halloween2020TheChild/CoquiDocker",
      "1684799206047"
    ],
    "https://github.com/Halloween2020TheChild/RazerHydraHIDJava.git": [
      "Halloween2020TheChild/RazerHydraHIDJava",
      "1685115421091"
    ],
    "https://github.com/madhephaestus/CoquiDocker.git": [
      "https://github.com/madhephaestus/CoquiDocker.git",
      "1684770068025"
    ],
    "https://gist.github.com/aa464b39c1208c357b8d4ae7fe210bbb.git": [
      "GIST: gsonExample.groovy",
      "1685639396909"
    ],
    "https://gist.github.com/f17ec09ad20e29590ea40a903b1f045d.git": [
      "GIST: Text To Speech example",
      "1684458375451"
    ],
    "https://github.com/Halloween2020TheChild/GroguMechanicsCad.git": [
      "Halloween2020TheChild/GroguMechanicsCad",
      "1684896439054"
    ],
    "https://github.com/madhephaestus/HortonsLinkages.git": [
      "madhephaestus/HortonsLinkages",
      "1683402339795"
    ],
    "https://github.com/madhephaestus/YoloJava.git": [
      "https://github.com/madhephaestus/YoloJava.git",
      "1684513907742"
    ],
    "https://github.com/madhephaestus/TextToSpeechASDRTest.git": [
      "https://github.com/madhephaestus/TextToSpeechASDRTest.git",
      "1684156722199"
    ],
    "https://gist.github.com/d4312a0787456ec27a2a.git": [
      "https://gist.github.com/d4312a0787456ec27a2a.git",
      "1685823081044"
    ],
    "https://github.com/Halloween2020TheChild/Zoltar.git": [
      "Halloween2020TheChild/Zoltar",
      "1683999087858"
    ]
  },
  "StadiaL8ZV-1c39": {},
  "katapult": {
    "gameControllerNames": [
      "Game",
      "Switch",
      "X-Box",
      "Dragon"
    ],
    "linkDeviceName": "kevkat",
    "robotName": "MediumKat",
    "robotGitFile": "MediumKat.xml",
    "robotGit": "https://github.com/OperationSmallKat/greycat.git"
  },
  "Microsoft X-Box 360 pad": {
    "A": "a-mode",
    "B": "b-mode",
    "Start": "start",
    "rx": "r-joy-left-right",
    "ry": "r-joy-up-down",
    "Mode": "select",
    "rz": "analog-trig",
    "Right Thumb": "r-trig-button",
    "x": "l-joy-left-right",
    "X": "x-mode",
    "Select": "select",
    "y": "l-joy-up-down",
    "Y": "y-mode",
    "Left Thumb": "l-trig-button"
  },
  "Performance Designed Products Faceoff Premiere Wired Pro Controller for Nintendo Switch": {
    "A": "y-mode",
    "B": "b-mode",
    "C": "a-mode",
    "Mode": "start",
    "rz": "r-joy-up-down",
    "Right Thumb": "analog-trig",
    "x": "l-joy-left-right",
    "X": "x-mode",
    "y": "l-joy-up-down",
    "Y": "l-trig-button",
    "Left Thumb 3": "select",
    "Right Thumb 2": "select",
    "z": "r-joy-left-right",
    "Z": "r-trig-button",
    "Left Thumb": "l-trig-button"
  },
  "studio-open-web": {},
  "Saitek PLC Saitek P2600 Rumble Force Pad": {
    "jogKinz": "rz",
    "jogLink": "x",
    "jogKinslider": "slider",
    "jogKiny": "y",
    "jogKinx": "x"
  },
  "MenueSettings": {
    "printCSG": false
  },
  "studio-open-git": {
    "https://github.com/Halloween2020TheChild/Zoltar.git:ZoltarController.groovy": [
      "https://github.com/Halloween2020TheChild/Zoltar.git",
      "ZoltarController.groovy"
    ],
    "https://github.com/madhephaestus/YoloJava.git:ResnetWithCamera.groovy": [
      "https://github.com/madhephaestus/YoloJava.git",
      "ResnetWithCamera.groovy"
    ],
    "https://github.com/Halloween2020TheChild/GroguMechanicsCad.git:hephaestus.xml": [
      "https://github.com/Halloween2020TheChild/GroguMechanicsCad.git",
      "hephaestus.xml"
    ]
  },
  "PDP CO.,LTD. Faceoff Wired Pro Controller for Nintendo Switch": {
    "A": "y-mode",
    "B": "b-mode",
    "C": "a-mode",
    "Mode": "start",
    "rz": "r-joy-up-down",
    "x": "l-joy-left-right",
    "X": "x-mode",
    "y": "l-joy-up-down",
    "Y": "l-trig-button",
    "Right Thumb 2": "select",
    "z": "r-joy-left-right",
    "Z": "r-trig-button",
    "Left Thumb": "analog-trig"
  },
  "BowlerStudioConfigs": {
    "tutorialSource": "https://github.com/CommonWealthRobotics/CommonWealthRobotics.github.io.git",
    "firstVersion": "1.45.6",
    "tutorialBranch": "deploy",
    "showTerminal": true,
    "tutorialBaseUrl": "/BowlerStudio/Welcome-To-BowlerStudio/",
    "fontsize": 18.0,
    "skinBranch": "1.45.5",
    "showDevices": true,
    "skinRepo": "https://github.com/madhephaestus/BowlerStudioImageAssets.git",
    "notifiedArduinoDep": true,
    "currentVersion": "1.45.6",
    "showCreatureLab": true
  }
}