{
  "Performance Designed Products Faceoff Deluxe+ Audio Wired Controller for Nintendo Switch": {
    "A": "y-mode",
    "B": "b-mode",
    "C": "a-mode",
    "Mode": "start",
    "rz": "r-joy-up-down",
    "Right Thumb": "analog-trig",
    "x": "l-joy-left-right",
    "X": "x-mode",
    "y": "l-joy-up-down",
    "Y": "l-trig-button",
    "Left Thumb 3": "select",
    "z": "r-joy-left-right",
    "Z": "r-trig-button"
  },
  "Microsoft X-Box 360 pad": {
    "A": "a-mode",
    "B": "b-mode",
    "Start": "start",
    "rx": "r-joy-left-right",
    "ry": "r-joy-up-down",
    "rz": "analog-trig",
    "Right Thumb": "r-trig-button",
    "x": "l-joy-left-right",
    "X": "x-mode",
    "Select": "select",
    "y": "l-joy-up-down",
    "Y": "y-mode",
    "Left Thumb": "l-trig-button"
  },
  "workspace": {
    "https://github.com/madhephaestus/carl-the-hexapod.git": [
      "madhephaestus/carl-the-hexapod",
      "1665949053140"
    ],
    "https://github.com/madhephaestus/fractaltree.git": [
      "https://github.com/madhephaestus/fractaltree.git",
      "1672085584896"
    ],
    "https://gist.github.com/4814b39ee72e9f590757.git": [
      "GIST: JavaCadExample",
      "1666308465759"
    ],
    "https://gist.github.com/cf5578c406644e7e4fe5447a698f85d5.git": [
      "GIST: Cap screw generator",
      "1673547157538"
    ],
    "https://github.com/madhephaestus/ahhhhhhhhhh.git": [
      "https://github.com/madhephaestus/ahhhhhhhhhh.git",
      "1671775712317"
    ],
    "https://github.com/madhephaestus/potbot.git": [
      "madhephaestus/potbot",
      "1673211621539"
    ],
    "https://github.com/Halloween2022RodPuppet/RodPuppetKinematics.git": [
      "Halloween2022RodPuppet/RodPuppetKinematics",
      "1665943905383"
    ],
    "https://gist.github.com/9655185a6b0f3a230158.git": [
      "GIST: .gitignore",
      "1666309814816"
    ],
    "https://gist.github.com/09a7c973ba854d9b8d35.git": [
      "https://gist.github.com/09a7c973ba854d9b8d35.git",
      "1665943713897"
    ],
    "https://github.com/madhephaestus/heatedThreadedInsertCadGenerator.git": [
      "madhephaestus/heatedThreadedInsertCadGenerator",
      "1667521964617"
    ],
    "https://github.com/OperationSmallKat/Luna.git": [
      "OperationSmallKat/Luna",
      "1665943713549"
    ],
    "https://github.com/madhephaestus/Fanuc_LR_Mate_200id_7L.git": [
      "madhephaestus/Fanuc_LR_Mate_200id_7L",
      "1666619795836"
    ],
    "https://github.com/Halloween2020TheChild/GroguMechanicsCad.git": [
      "Halloween2020TheChild/GroguMechanicsCad",
      "1667521963240"
    ],
    "https://github.com/madhephaestus/LewanSoulHornCadGenerator.git": [
      "madhephaestus/LewanSoulHornCadGenerator",
      "1667521965071"
    ],
    "https://github.com/madhephaestus/RoundMotorVitamin.git": [
      "madhephaestus/RoundMotorVitamin",
      "1673547156209"
    ],
    "https://github.com/madhephaestus/basicincomeviatransactiontax.git": [
      "madhephaestus/basicincomeviatransactiontax",
      "1670634456176"
    ],
    "https://github.com/madhephaestus/sequencetest.git": [
      "https://github.com/madhephaestus/sequencetest.git",
      "1666719458963"
    ],
    "https://github.com/madhephaestus/manipulator-test.git": [
      "madhephaestus/manipulator-test",
      "1672641073059"
    ],
    "https://github.com/madhephaestus/GearGenerator.git": [
      "madhephaestus/GearGenerator",
      "1673547155579"
    ],
    "https://github.com/OperationSmallKat/SmallKat_V2.git": [
      "https://github.com/OperationSmallKat/SmallKat_V2.git",
      "1665943712389"
    ]
  },
  "Performance Designed Products Faceoff Premiere Wired Pro Controller for Nintendo Switch": {
    "A": "y-mode",
    "B": "b-mode",
    "C": "a-mode",
    "Mode": "start",
    "rz": "r-joy-up-down",
    "Right Thumb": "analog-trig",
    "x": "l-joy-left-right",
    "X": "x-mode",
    "y": "l-joy-up-down",
    "Y": "l-trig-button",
    "Left Thumb 3": "select",
    "z": "r-joy-left-right",
    "Z": "r-trig-button"
  },
  "studio-open-web": {},
  "katapult": {
    "gameControllerNames": [
      "Dragon",
      "X-Box",
      "Game",
      "Switch"
    ],
    "linkDeviceName": "midnight",
    "robotName": "Luna",
    "robotGitFile": "MediumKat.xml",
    "robotGit": "https://github.com/OperationSmallKat/Luna.git"
  },
  "studio-open-git": {
    "https://github.com/Halloween2022RodPuppet/RodPuppetKinematics.git:animation.groovy": [
      "https://github.com/Halloween2022RodPuppet/RodPuppetKinematics.git",
      "animation.groovy"
    ],
    "https://github.com/madhephaestus/fractaltree.git:tree.groovy": [
      "https://github.com/madhephaestus/fractaltree.git",
      "tree.groovy"
    ],
    "https://github.com/madhephaestus/arduinotest.git:arduinotest.ino": [
      "https://github.com/madhephaestus/arduinotest.git",
      "arduinotest.ino"
    ],
    "https://github.com/madhephaestus/potbot.git:robotBase.groovy": [
      "https://github.com/madhephaestus/potbot.git",
      "robotBase.groovy"
    ]
  },
  "PDP CO.,LTD. Faceoff Wired Pro Controller for Nintendo Switch": {
    "A": "y-mode",
    "B": "b-mode",
    "C": "a-mode",
    "Mode": "start",
    "rz": "r-joy-up-down",
    "x": "l-joy-left-right",
    "X": "x-mode",
    "y": "l-joy-up-down",
    "Y": "l-trig-button",
    "Right Thumb 2": "select",
    "z": "r-joy-left-right",
    "Z": "r-trig-button",
    "Left Thumb": "analog-trig"
  },
  "BowlerStudioConfigs": {
    "tutorialSource": "https://github.com/CommonWealthRobotics/CommonWealthRobotics.github.io.git",
    "firstVersion": "1.45.6",
    "tutorialBranch": "deploy",
    "tutorialBaseUrl": "/BowlerStudio/Welcome-To-BowlerStudio/",
    "fontsize": 12.0,
    "skinBranch": "1.45.5",
    "skinRepo": "https://github.com/madhephaestus/BowlerStudioImageAssets.git",
    "notifiedArduinoDep": true,
    "currentVersion": "1.45.6"
  }
}